typ2anki/__init__.py
typ2anki/api.py
typ2anki/generator.py
typ2anki/get_data.py
typ2anki/main.py
typ2anki/parse.py
typ2anki/process.py
typ2anki-0.1.1.dist-info/LICENSE
typ2anki-0.1.1.dist-info/METADATA
typ2anki-0.1.1.dist-info/WHEEL
typ2anki-0.1.1.dist-info/entry_points.txt
typ2anki-0.1.1.dist-info/top_level.txt
typ2anki-0.1.1.dist-info/RECORD
